yuna/__init__.py
yuna/__main__.py
yuna/cell_labels.py
yuna/datafield.py
yuna/deck.py
yuna/devices.py
yuna/docopt.py
yuna/masternodes.py
yuna/metals.py
yuna/model.py
yuna/overdrive.py
yuna/polygons.py
yuna/process.py
yuna/terminal.py
yuna/user_labels.py
yuna/utils.py
yuna-1.0.6.dist-info/METADATA
yuna-1.0.6.dist-info/RECORD
yuna-1.0.6.dist-info/WHEEL
yuna-1.0.6.dist-info/entry_points.txt
yuna-1.0.6.dist-info/top_level.txt
