Metadata-Version: 2.1
Name: yuna
Version: 1.0.6
Summary: Processes the layers from a GDS file.
Home-page: https://github.com/rubenvanstaden/yuna
Author: Ruben van Staden
Author-email: rubenvanstaden@gmail.com
License: BSD
Keywords: yuna
Platform: UNKNOWN
Requires-Dist: gdspy
Requires-Dist: shapely
Requires-Dist: pyclipper
Requires-Dist: setuptools
Requires-Dist: numpy
Requires-Dist: matplotlib
Requires-Dist: docopt
Requires-Dist: future
Requires-Dist: termcolor
